llmbench/__init__.py
llmbench/cli/__init__.py
llmbench/cli/token_benchmark.py
llmbench/common/__init__.py
llmbench/common/constants.py
llmbench/data.py
llmbench/inference/__init__.py
llmbench/inference/clients/__init__.py
llmbench/inference/clients/client_abc.py
llmbench/inference/clients/client_openai.py
llmbench/inference/clients/client_test.py
llmbench/inference/clients/request_data.py
llmbench/inference/general_client.py
llmbench/inference/token_benchmark.py
llmbench/report.py
llmbench/utils.py
llmbench_cmri-0.1.8.dist-info/entry_points.txt
llmbench_cmri-0.1.8.dist-info/LICENSE.txt
llmbench_cmri-0.1.8.dist-info/METADATA
llmbench_cmri-0.1.8.dist-info/NOTICE.txt
llmbench_cmri-0.1.8.dist-info/WHEEL
llmbench_cmri-0.1.8.dist-info/RECORD
